docprocessor/__init__.py
docprocessor/config.py
docprocessor/exceptions.py
docprocessor/processor.py
docprocessor/core/__init__.py
docprocessor/core/chunker.py
docprocessor/core/extractor.py
docprocessor/core/ocr.py
docprocessor/core/summarizer.py
docprocessor/integrations/__init__.py
docprocessor/integrations/meilisearch_indexer.py
docprocessor-1.0.0.dist-info/licenses/LICENSE
docprocessor-1.0.0.dist-info/METADATA
docprocessor-1.0.0.dist-info/WHEEL
docprocessor-1.0.0.dist-info/top_level.txt
docprocessor-1.0.0.dist-info/RECORD
