Metadata-Version: 2.4
Name: docprocessor
Version: 1.0.0
Summary: Intelligent document processing with OCR, chunking, and AI summarization
Home-page: https://github.com/Knowledge-Innovation-Centre/doc-processor
Author: Knowledge Innovation Centre
Author-email: Knowledge Innovation Centre <info@knowledgeinnovation.eu>
License: MIT
Project-URL: Homepage, https://github.com/Knowledge-Innovation-Centre/doc-processor
Project-URL: Documentation, https://github.com/Knowledge-Innovation-Centre/doc-processor#readme
Project-URL: Repository, https://github.com/Knowledge-Innovation-Centre/doc-processor
Project-URL: Bug Tracker, https://github.com/Knowledge-Innovation-Centre/doc-processor/issues
Project-URL: Changelog, https://github.com/Knowledge-Innovation-Centre/doc-processor/blob/main/CHANGELOG.md
Keywords: document-processing,ocr,nlp,meilisearch,ai,pdf,chunking,summarization
Classifier: Development Status :: 4 - Beta
Classifier: Intended Audience :: Developers
Classifier: License :: OSI Approved :: MIT License
Classifier: Programming Language :: Python :: 3
Classifier: Programming Language :: Python :: 3.10
Classifier: Programming Language :: Python :: 3.11
Classifier: Programming Language :: Python :: 3.12
Classifier: Topic :: Software Development :: Libraries :: Python Modules
Classifier: Topic :: Text Processing
Classifier: Topic :: Scientific/Engineering :: Artificial Intelligence
Requires-Python: >=3.9
License-File: LICENSE
Requires-Dist: meilisearch>=0.30.0
Requires-Dist: langchain-text-splitters>=0.2.0
Requires-Dist: tiktoken>=0.5.0
Requires-Dist: pdfminer.six>=20240706
Requires-Dist: pdf2image>=1.17.0
Requires-Dist: pillow>=11.0.0
Requires-Dist: pytesseract>=0.3.13
Requires-Dist: opencv-python>=4.8.0
Requires-Dist: python-docx>=1.1.0
Provides-Extra: dev
Requires-Dist: pytest>=8.0.0; extra == "dev"
Requires-Dist: pytest-cov>=4.0.0; extra == "dev"
Requires-Dist: pytest-asyncio>=0.21.0; extra == "dev"
Requires-Dist: pytest-mock>=3.12.0; extra == "dev"
Requires-Dist: black>=24.0.0; extra == "dev"
Requires-Dist: isort>=5.12.0; extra == "dev"
Requires-Dist: flake8>=7.0.0; extra == "dev"
Requires-Dist: mypy>=1.8.0; extra == "dev"
Requires-Dist: pre-commit>=3.6.0; extra == "dev"
Requires-Dist: reportlab>=4.0.0; extra == "dev"
Provides-Extra: docs
Requires-Dist: sphinx>=7.0.0; extra == "docs"
Requires-Dist: sphinx-rtd-theme>=2.0.0; extra == "docs"
Requires-Dist: sphinx-autodoc-typehints>=1.25.0; extra == "docs"
Provides-Extra: all
Requires-Dist: docprocessor[dev,docs]; extra == "all"
Dynamic: author
Dynamic: home-page
Dynamic: license-file
Dynamic: requires-python
